plot_coverage/__init__.py
plot_coverage/cli.py
plot_coverage/plot_coverage.py
plot_coverage-1.0.2.dist-info/AUTHORS.rst
plot_coverage-1.0.2.dist-info/LICENSE
plot_coverage-1.0.2.dist-info/METADATA
plot_coverage-1.0.2.dist-info/WHEEL
plot_coverage-1.0.2.dist-info/entry_points.txt
plot_coverage-1.0.2.dist-info/top_level.txt
plot_coverage-1.0.2.dist-info/RECORD
