Metadata-Version: 2.1
Name: plot-coverage
Version: 1.0.2
Summary: Python package to generate plots from coverage report
Home-page: https://github.com/modasserbillah/plot_coverage
Author: Modasser Billah
Author-email: imtishad@gmail.com
License: BSD license
Keywords: plot_coverage
Platform: UNKNOWN
Classifier: Development Status :: 2 - Pre-Alpha
Classifier: Intended Audience :: Developers
Classifier: License :: OSI Approved :: BSD License
Classifier: Natural Language :: English
Classifier: Programming Language :: Python :: 3
Classifier: Programming Language :: Python :: 3.6
Classifier: Programming Language :: Python :: 3.7
Classifier: Programming Language :: Python :: 3.8
Requires-Python: >=3.6
Requires-Dist: Click (>=7.0)
Requires-Dist: beautifulsoup4 (==4.9.1)
Requires-Dist: html5lib (==1.1)
Requires-Dist: pandas (==1.0.5)
Requires-Dist: plotly (==4.8.1)
Requires-Dist: lxml (==4.5.1)
